examples/__init__.py
examples/lending_example.py
examples/weighted_model_example.py
monetary_classifier/__init__.py
monetary_classifier/monetary_classifier.py
monetary_classifier-0.1.0.dist-info/licenses/LICENSE
tests/__init__.py
tests/test_monetary_classifier.py
monetary_classifier-0.1.0.dist-info/METADATA
monetary_classifier-0.1.0.dist-info/WHEEL
monetary_classifier-0.1.0.dist-info/top_level.txt
monetary_classifier-0.1.0.dist-info/RECORD
