Metadata-Version: 2.4
Name: monetary-classifier
Version: 0.1.0
Summary: A scikit-learn compatible package for classification with monetary outcomes
Home-page: https://github.com/yourusername/monetary-classifier
Author: Your Name
Author-email: your.email@example.com
Classifier: Programming Language :: Python :: 3
Classifier: License :: OSI Approved :: MIT License
Classifier: Operating System :: OS Independent
Classifier: Intended Audience :: Science/Research
Classifier: Topic :: Scientific/Engineering :: Artificial Intelligence
Requires-Python: >=3.7
License-File: LICENSE
Requires-Dist: numpy>=1.17.0
Requires-Dist: scikit-learn>=0.24.0
Requires-Dist: pandas>=1.0.0
Requires-Dist: matplotlib>=3.0.0
Provides-Extra: xgboost
Requires-Dist: xgboost>=1.0.0; extra == "xgboost"
Provides-Extra: lightgbm
Requires-Dist: lightgbm>=3.0.0; extra == "lightgbm"
Provides-Extra: catboost
Requires-Dist: catboost>=0.24.0; extra == "catboost"
Provides-Extra: dev
Requires-Dist: pytest>=6.0.0; extra == "dev"
Requires-Dist: flake8>=3.8.0; extra == "dev"
Requires-Dist: black>=20.8b1; extra == "dev"
Dynamic: author
Dynamic: author-email
Dynamic: classifier
Dynamic: description
Dynamic: description-content-type
Dynamic: home-page
Dynamic: license-file
Dynamic: provides-extra
Dynamic: requires-dist
Dynamic: requires-python
Dynamic: summary
